openctm/__init__.py
openctm/binding.py
openctm-0.0.6.dist-info/LICENSE.md
openctm-0.0.6.dist-info/METADATA
openctm-0.0.6.dist-info/WHEEL
openctm-0.0.6.dist-info/top_level.txt
openctm-0.0.6.dist-info/RECORD
