Metadata-Version: 2.1
Name: openctm
Version: 0.0.6
Summary: Provide a loader for OpenCTM files
Author-email: Michael Dawson-Haggerty <mikedh@kerfed.com>
License: MIT License
Project-URL: Homepage, https://github.com/trimesh/openctm
Keywords: graphics,OpenCTM
Classifier: Programming Language :: Python
Classifier: Programming Language :: Python :: 3.7
Classifier: Programming Language :: Python :: 3.8
Classifier: Programming Language :: Python :: 3.9
Classifier: Programming Language :: Python :: 3.10
Classifier: Programming Language :: Python :: 3.11
Classifier: Programming Language :: Python :: 3.12
Classifier: Natural Language :: English
Classifier: Topic :: Scientific/Engineering
Classifier: Topic :: Multimedia :: Graphics
Classifier: Topic :: Multimedia :: Graphics :: 3D Modeling
Requires-Python: >=3.7
License-File: LICENSE.md
Requires-Dist: numpy
Provides-Extra: tests
Requires-Dist: pytest; extra == "tests"
Requires-Dist: trimesh; extra == "tests"
